setup.cfg
setup.py
liquidplanner/__init__.py
liquidplanner/api.py
liquidplanner/auth.py
liquidplanner/exceptions.py
liquidplanner/manager.py
liquidplanner/models.py
liquidplanner/utils.py
pyliquidplanner.egg-info/PKG-INFO
pyliquidplanner.egg-info/SOURCES.txt
pyliquidplanner.egg-info/dependency_links.txt
pyliquidplanner.egg-info/pbr.json
pyliquidplanner.egg-info/requires.txt
pyliquidplanner.egg-info/top_level.txt