Metadata-Version: 1.1
Name: pyliquidplanner
Version: 0.0.1
Summary: Python library for accessing the REST API of the Liquid Planner project management tool
Home-page: https://github.com/gavinhodge/pyliquidplanner
Author: Gavin Hodge
Author-email: gavin.hodge@gmail.com
License: MIT
Download-URL: https://github.com/gavinhodge/pyliquidplanner/tarball/0.0.1
Keywords: liquidplanner,liquid,planner,project,management
Platform: UNKNOWN
